quantizer/__init__.py
quantizer/controller.py
quantizer/envelope.py
quantizer/fx.py
quantizer/oscillator.py
quantizer/sequencer.py
quantizer/stream.py
quantizer/wavetable.py
quantizer/kernel/__init__.py
quantizer/kernel/kontext.py
quantizer/kernel/util.py
quantizer/kernel/waveform.py
quantizer-0.2.1.dist-info/LICENSE.txt
quantizer-0.2.1.dist-info/METADATA
quantizer-0.2.1.dist-info/WHEEL
quantizer-0.2.1.dist-info/top_level.txt
quantizer-0.2.1.dist-info/RECORD
