Metadata-Version: 2.1
Name: quantizer
Version: 0.2.1
Summary: an object-oriented audio synthesis framework
Home-page: https://github.com/ulrichtsblr/quantizer
Author: BLR Ulrichts
Author-email: ulrichts.blr@protonmail.com
License: UNKNOWN
Platform: UNKNOWN
Classifier: License :: OSI Approved :: GNU General Public License v3 (GPLv3)
Classifier: Programming Language :: Python :: 3
Classifier: Operating System :: OS Independent
Requires-Python: >=3.7
License-File: LICENSE.txt
Requires-Dist: matplotlib (>=3.0)
Requires-Dist: numba (>=0.42numpy>=1.15)
Requires-Dist: pyyaml (>=5.1)
Requires-Dist: scipy (>=1.2)
Requires-Dist: sounddevice (>=0.4)
